Workbook

Sheet Read me
A1: Philbrick content audit
A3: What this workbook is | B3: Every piece of text on the new Philbrick website, page by page, next to the equivalent text on the current WordPress site.
A4: What to do | B4: Type the final approved wording in the yellow 'Client Final Text' column. Leave a cell blank to keep the current website text as it is.
A6: Sheet | B6: What it covers
A7: Site content | B7: Every heading, paragraph, list item, button and link on the company pages (home, about, contact, policies and so on).
A8: Product content | B8: The same, for all 14 product categories and 21 product pages.
A9: Global elements | B9: Header, footer, contact details, statutory numbers and social links, which repeat on every page.
A10: SEO & meta | B10: Browser titles and Google descriptions, one pair per page.
A11: WordPress source | B11: Every page on the current WordPress site, what it contained, and where that content now lives.
A12: Product source | B12: The WordPress product records behind each product page: how many salient features and whether a specification table was carried across.
A14: Status column | B14: Meaning
A15: Matches WordPress | B15: The text is the client's own wording from the WordPress site, unchanged.
A16: Adapted from WordPress | B16: The client's own content, re-punctuated or split up for the new layout. The facts are unchanged.
... A20: Confirm with client | B20: A name or role we could not verify from the WordPress site.
A22: Colour key
A23: Yellow cells | B23: For you to fill in.
A24: Pink rows | B24: Need a decision: placeholder text, an unverified number or a name.
A25: Green rows | B25: Already match the WordPress site; usually nothing to do.

Sheet Summary
A1: Content audit summary
A2: Counts update automatically as the Status columns are edited.
A4: Status | B4: Site content | C4: Product content | D4: Global elements | E4: Total
A5: Matches WordPress | B5: =COUNTIF('Site content'!$G$2:$G$556,$A5) | C5: =COUNTIF('Product content'!$G$2:$G$887,$A5) | D5: =COUNTIF('Global elements'!$G$2:$G$31,$A5) | E5: =SUM(B5:D5)
A6: Adapted from WordPress | B6: =COUNTIF('Site content'!$G$2:$G$556,$A6) | C6: =COUNTIF('Product content'!$G$2:$G$887,$A6) | D6: =COUNTIF('Global elements'!$G$2:$G$31,$A6) | E6: =SUM(B6:D6)
A7: New copy (not on WordPress) | B7: =COUNTIF('Site content'!$G$2:$G$556,$A7) | C7: =COUNTIF('Product content'!$G$2:$G$887,$A7) | D7: =COUNTIF('Global elements'!$G$2:$G$31,$A7) | E7: =SUM(B7:D7)
A8: Placeholder - needs client input | B8: =COUNTIF('Site content'!$G$2:$G$556,$A8) | C8: =COUNTIF('Product content'!$G$2:$G$887,$A8) | D8: =COUNTIF('Global elements'!$G$2:$G$31,$A8) | E8: =SUM(B8:D8)
A9: Statistic - confirm with client | B9: =COUNTIF('Site content'!$G$2:$G$556,$A9) | C9: =COUNTIF('Product content'!$G$2:$G$887,$A9) | D9: =COUNTIF('Global elements'!$G$2:$G$31,$A9) | E9: =SUM(B9:D9)
A10: Confirm with client | B10: =COUNTIF('Site content'!$G$2:$G$556,$A10) | C10: =COUNTIF('Product content'!$G$2:$G$887,$A10) | D10: =COUNTIF('Global elements'!$G$2:$G$31,$A10) | E10: =SUM(B10:D10)
A11: Approved | B11: =COUNTIF('Site content'!$G$2:$G$556,$A11) | C11: =COUNTIF('Product content'!$G$2:$G$887,$A11) | D11: =COUNTIF('Global elements'!$G$2:$G$31,$A11) | E11: =SUM(B11:D11)
A12: Changed | B12: =COUNTIF('Site content'!$G$2:$G$556,$A12) | C12: =COUNTIF('Product content'!$G$2:$G$887,$A12) | D12: =COUNTIF('Global elements'!$G$2:$G$31,$A12) | E12: =SUM(B12:D12)
A13: All items | B13: =SUM(B5:B12) | C13: =SUM(C5:C12) | D13: =SUM(D5:D12) | E13: =SUM(E5:E12)
A15: Pages audited | B15: 58
A16: WordPress pages reviewed | B16: 16
A17: WordPress products migrated | B17: 38

Sheet Site content
A1: Page URL | B1: Section | C1: Item type | D1: Current Website Text | E1: Suggested / WordPress Text | F1: Client Final Text | G1: Status
A2: /about | B2: Who we are · Engineering elevator solutions | C2: Paragraph | D2: Philbrick Controls India was founded in 1992 in Ahmedabad… | E2: Same as WordPress | F2: Philbrick Controls India was established in 1992 at Ahmedabad… | G2: Changed
A3: / | B3: 01 Who we are · Engineering elevator solutions since 1992. | C3: Heading | D3: Engineering elevator solutions since 1992. | G3: New copy (not on WordPress)
A4: / | B4: 01 Who we are · Engineering elevator solutions since 1992. | C4: Paragraph | D4: Philbrick Controls India was founded in 1992 in Ahmedabad with a main focus on providing automation solutions by research and development and production of Control Instruments and Control Panels. We have a dedicated team with a special focus on Elevator Industry for providing Smarter, Safer and Simpler Control Panels and various accessories for the passenger lift. | E4: Reworded from the WordPress page: Company | G4: Adapted from WordPress
A5: / | B5: 01 Who we are · Engineering elevator solutions since 1992. | C5: Paragraph | D5: Years of engineering | G5: New copy (not on WordPress)
A6: / | B6: 01 Who we are · Engineering elevator solutions since 1992. | C6: Paragraph | D6: Product categories | G6: New copy (not on WordPress)
A7: / | B7: 01 Who we are · Engineering elevator solutions since 1992. | C7: Paragraph | D7: In-house units | G7: New copy (not on WordPress)
A8: / | B8: 01 Who we are · Engineering elevator solutions since 1992. | C8: Link | D8: Our story | G8: New copy (not on WordPress)
A9: / | B9: 01 Who we are · Engineering elevator solutions since 1992. | C9: Paragraph | D9: Philbrick · engineering since 1992 | G9: New copy (not on WordPress)
A10: / | B10: 02 The range · Everything an elevator needs. | C10: Heading | D10: Everything an elevator needs. | G10: New copy (not on WordPress)
A11: / | B11: 02 The range · Everything an elevator needs. | C11: Paragraph | D11: Control, safety, doors, cabins and signalling: Philbrick engineers and builds the components that make a lift run, all under one roof. | G11: New copy (not on WordPress)
A12: / | B12: 02 The range · Everything an elevator needs. | C12: Link | D12: All products | G12: New copy (not on WordPress)
A13: / | B13: 02 The range · Everything an elevator needs. | C13: Paragraph | D13: The Philbrick system | G13: New copy (not on WordPress)
A14: / | B14: 02 The range · Everything an elevator needs. | C14: Paragraph | D14: Every component, one source | G14: New copy (not on WordPress)
A15: / | B15: 02 The range · Everything an elevator needs. | C15: List item | D15: Control & Drives Elevator Control Panel | G15: New copy (not on WordPress)
A16: / | B16: 02 The range · Everything an elevator needs. | C16: List item | D16: Signalling Elevator Display | G16: New copy (not on WordPress)
... A49: /about | B49: Our story · Elevator solutions, engineered in Ahmedabad since 1992 | C49: Page title | D49: Elevator solutions, engineered in Ahmedabad since 1992 | G49: New copy (not on WordPress)
A50: /about | B50: Our story · Elevator solutions, engineered in Ahmedabad since 1992 | C50: Paragraph | D50: Providing automation solutions by research and development and production of Control Instruments, Control Panels and elevator accessories, with a dedicated team focused on Smarter, Safer and Simpler solutions for the passenger lift. | E50: Reworded from the WordPress page: Company | G50: Adapted from WordPress
A51: /about | B51: Our story · Elevator solutions, engineered in Ahmedabad since 1992 | C51: Paragraph | D51: Since 1992, Ahmedabad | G51: New copy (not on WordPress)
A52: /about | B52: Our story · Elevator solutions, engineered in Ahmedabad since 1992 | C52: Paragraph | D52: Control panels to fixtures | G52: New copy (not on WordPress)
A53: /about | B53: Our story · Elevator solutions, engineered in Ahmedabad since 1992 | C53: Paragraph | D53: Design · QC · procurement · warehousing | G53: New copy (not on WordPress)
A54: /about | B54: Our story · Elevator solutions, engineered in Ahmedabad since 1992 | C54: Paragraph | D54: Philbrick Controls India was founded in 1992 in Ahmedabad, a city of Gujarat, India with a main focus on providing automation solution by research and development and production of Control Instruments and Control Panels. A teamwork of young and professional entrepreneurial and engineers with apex of providing technical solution with economy, the proficiency, in depth techno-commercial knowledge has brought the results in front of you. | E54: Same wording as the WordPress page: Company | G54: Matches WordPress
A55: /about | B55: Activity · What we do, and who we do it for | C55: Heading | D55: What we do, and who we do it for | G55: New copy (not on WordPress)
A56: /about | B56: Activity · What we do, and who we do it for | C56: Paragraph | D56: Automation solutions built around the application, from microcontroller based instruments to complete control panels. | E56: Reworded from the WordPress page: Company | G56: Adapted from WordPress
A57: /about | B57: Activity · What we do, and who we do it for | C57: Paragraph | D57: Company provides automation solution to various industries by producing microcontroller based instruments and control panels. We are specialized in understanding the application to fulfil the industrial requirements by providing the best efficient economical solutions. We offer our best proficient automation solutions by advance development techniques, hi-tech manufacturing process, systematic testing methodology and strong quality assessment. | E57: Same wording as the WordPress page: Company | G57: Matches WordPress
A58: /about | B58: Activity · What we do, and who we do it for | C58: Paragraph | D58: We have been catering our services to various industrial segments like Construction, Textile, Steel, Plastic, Paper, Glass, Power, Chemical and Pollution Control Equipment manufacturers etc. We have dedicated team with a special focus on Elevator Industry for providing Smarter, Safer and Simpler Control Panels and various accessories for the passenger lift. | E58: Same wording as the WordPress page: Company | G58: Matches WordPress
A59: /about | B59: Activity · What we do, and who we do it for | C59: List item | D59: 01 Construction | G59: New copy (not on WordPress)
A60: /about | B60: Activity · What we do, and who we do it for | C60: List item | D60: 02 Textile | G60: New copy (not on WordPress)
A61: /about | B61: Activity · What we do, and who we do it for | C61: List item | D61: 03 Steel | G61: New copy (not on WordPress)
A62: /about | B62: Activity · What we do, and who we do it for | C62: List item | D62: 04 Plastic | G62: New copy (not on WordPress)
A63: /about | B63: Activity · What we do, and who we do it for | C63: List item | D63: 05 Paper | G63: New copy (not on WordPress)
A64: /about | B64: Activity · What we do, and who we do it for | C64: List item | D64: 06 Glass | G64: New copy (not on WordPress)
A65: /about | B65: Activity · What we do, and who we do it for | C65: List item | D65: 07 Power | G65: New copy (not on WordPress)
A66: /about | B66: Activity · What we do, and who we do it for | C66: List item | D66: 08 Chemical | G66: New copy (not on WordPress)
A67: /about | B67: Activity · What we do, and who we do it for | C67: List item | D67: 09 Pollution Control Equipment | G67: New copy (not on WordPress)
A68: /about | B68: History · From a temperature indicator to a complete elevator range | C68: Heading | D68: From a temperature indicator to a complete elevator range | G68: New copy (not on WordPress)
A69: /about | B69: History · From a temperature indicator to a complete elevator range | C69: Paragraph | D69: Three decades of products, each one answering a problem a customer brought to us. | G69: New copy (not on WordPress)
A70: /about | B70: History · From a temperature indicator to a complete elevator range | C70: List item | D70: 1992 The first instruments Philbrick started with low cost high performing Digital Temperature Indicators, Temperature Controllers and scanners. | E70: Reworded from the WordPress page: Company | G70: Adapted from WordPress
A71: /about | B71: History · From a temperature indicator to a complete elevator range | C71: List item | D71: 1994 PC-2000 replaces an import Introduction of Programmable Temperature Profile Controller PC-2000 for the Dyeing machine was accepted by most of the dyeing and printing process houses as a preferred option for the replacement of imported controller from outside India. | E71: Reworded from the WordPress page: Company | G71: Adapted from WordPress
A72: /about | B72: History · From a temperature indicator to a complete elevator range | C72: List item | D72: 1997 Into control panels, and into elevators With a remarkable success story OEM demanded the complete solution from Philbrick, which led the company to enter the market of Industrial control panels, and Philbrick started manufacturing Automation Control Panels in 1997. Having the brand image as a quality manufacturer, Elevator Manufacturers approached us for a solution to the conventional relay logic based hardwired control panel for passenger lift. Philbrick had started the first Microcontroller based elevator controller panel in Ahmedabad in 1997. | E72: Reworded from the WordPress page: Company | G72: Adapted from WordPress
A73: /about | B73: History · From a temperature indicator to a complete elevator range | C73: List item | D73: 1997 to 2005 The product basket fills As the preferred quality manufacturer image continued, manufacturers of other industries went on approaching, and the product basket filled with products like Digital Speed Indicator, Zero Speed Switch, Flame Failure Detection Unit, Burner Sequence Controller for boilers, various kinds of Timers, Bag filter sequential timers, Battery cell scanner, Flow totalizer for Asphalt Mixing Plant, Digital Weighing Scale, Weigh Feeder and Batch Weighing Controllers, Flame proof Equipments and so many customised automation and control solutions. | E73: Reworded from the WordPress page: Company | G73: Adapted from WordPress
A74: /about | B74: History · From a temperature indicator to a complete elevator range | C74: List item | D74: 2001 A new elevator controller series Company again broke traditional approach for Elevator Controller and introduced more featured Elevator Controller Series E203DL, E203VF and E203ADVF. Philbrick started other electronics accessories like Car Position/Direction display, Dot Matrix Scrolling display, Digital Clock and Temperature Indicator for COP, Phase sequence Changer, Emergency Light and Alarm, Door Close Announcer and Floor Announcing System. | E74: Reworded from the WordPress page: Company | G74: Adapted from WordPress
A75: /about | B75: History · From a temperature indicator to a complete elevator range | C75: List item | D75: 2008 Elevator+, I-Auto and Lift Master As innovation was the main principal, Philbrick kept the pace with the other Industrial Automation and started PLC and SCADA based control panels. The company's approach continued for the Elevator Industry also, and it introduced a new series of Elevator Controller, “Elevator+” and “I-Auto”, by 2008. During the same time other electronics accessories for elevators were also introduced, like Monochrome LCD, Full colour TFT and Touch Panel COP. Philbrick was worried about the high cost and failure of Imported Electronics Controllers for Automatic Door operators and started an indigenous solution for the door operator, “LIFT MASTER”, which was accepted everywhere. | E75: Reworded from the WordPress page: Company | G75: Adapted from WordPress
A76: /about | B76: History · From a temperature indicator to a complete elevator range | C76: List item | D76: 2009 A new campus, and Synergy As the company was growing with good acceleration, to strengthen the infrastructure and manufacturing capabilities Philbrick shifted to a new well organised campus having 10,000 sq feet of working area with latest manufacturing facilities and campus wide LAN connectivity in May 2009. The new infrastructure came with a boost: as a first result Philbrick started manufacturing “Synergy” brand Automatic Door Operator, commencing with the “Ultima” series. | E76: Reworded from the WordPress page: Company | G76: Adapted from WordPress
A77: /about | B77: History · From a temperature indicator to a complete elevator range | C77: List item | D77: 2012 The Xpert motherboard series The success journey continues, and in 2012 Philbrick introduced the new more featured motherboard series “Xpert”. We also added some advancement in other accessories and introduced FA300, RFID and Biometric access for Lift. | E77: Reworded from the WordPress page: Company | G77: Adapted from WordPress
A78: /about | B78: History · From a temperature indicator to a complete elevator range | C78: List item | D78: 2014 Tie up with STEP In the year 2014 the new trend of Integrated Elevator Controller arose. Philbrick did the tie up with the largest Chinese manufacturer of Elevator products, named “STEP”, to keep its image as trend setter. | E78: Reworded from the WordPress page: Company | G78: Adapted from WordPress
A79: /about | B79: History · From a temperature indicator to a complete elevator range | C79: List item | D79: 2019 Infrastructure doubled In 2019, to fulfil the market demand, Philbrick doubled its infrastructure facility. | E79: Reworded from the WordPress page: Company | G79: Adapted from WordPress
A80: /about | B80: History · From a temperature indicator to a complete elevator range | C80: List item | D80: Today High tech R&D and manufacturing Today Philbrick is an organization having high tech equipped R&D manufacturing infrastructure backboned by a Highly Qualified Engineers' team, skilled technicians and ERP. Philbrick will endeavour to improve every aspect of daily life for people and bring new thoughts and new life to society. | E80: Reworded from the WordPress page: Company | G80: Adapted from WordPress
A81: /about | B81: History · From a temperature indicator to a complete elevator range | C81: Paragraph | D81: See the milestone timeline → | G81: New copy (not on WordPress)
A82: /about | B82: Infrastructure · Manufacturing & engineering, built in-house | C82: Heading | D82: Manufacturing & engineering, built in-house | G82: New copy (not on WordPress)
A83: /about | B83: Infrastructure · Manufacturing & engineering, built in-house | C83: Paragraph | D83: Dedicated units for procurement, design, quality control, warehousing and packaging keep quality and lead time in our own hands. | G83: New copy (not on WordPress)
A84: /about | B84: Infrastructure · Manufacturing & engineering, built in-house | C84: Subheading | D84: In-house manufacturing | G84: New copy (not on WordPress)
A85: /about | B85: Infrastructure · Manufacturing & engineering, built in-house | C85: Paragraph | D85: A well organised campus with 10,000+ sq feet of working area with latest manufacturing facilities and LAN connectivity, doubled in 2019 to meet growing market demand. | E85: Reworded from the WordPress page: Company | G85: Adapted from WordPress
A86: /about | B86: Infrastructure · Manufacturing & engineering, built in-house | C86: Subheading | D86: Design & R&D | G86: New copy (not on WordPress)
A87: /about | B87: Infrastructure · Manufacturing & engineering, built in-house | C87: Paragraph | D87: High tech equipped R&D infrastructure backed by Highly Qualified Engineers' team, skilled technicians and ERP, dedicated to developing control, door-operator, safety and display products. | E87: Reworded from the WordPress page: Company | G87: Adapted from WordPress
A88: /about | B88: Infrastructure · Manufacturing & engineering, built in-house | C88: Subheading | D88: Quality control | G88: New copy (not on WordPress)
A89: /about | B89: Infrastructure · Manufacturing & engineering, built in-house | C89: Paragraph | D89: Strict quality checks, records and test certificates as per ISO certification. Each part undergoes stage wise and final inspection as per Q.A. plan and tested as per Indian standard specification. | E89: Reworded from the WordPress page: Quality Policy | G89: Adapted from WordPress
A90: /about | B90: Infrastructure · Manufacturing & engineering, built in-house | C90: Subheading | D90: Procurement | G90: New copy (not on WordPress)
A91: /about | B91: Infrastructure · Manufacturing & engineering, built in-house | C91: Paragraph | D91: A structured procurement unit sources materials and parts reliably, keeping production supplied and consistent. | G91: New copy (not on WordPress)
A92: /about | B92: Infrastructure · Manufacturing & engineering, built in-house | C92: Subheading | D92: Warehousing & packaging | G92: New copy (not on WordPress)
A93: /about | B93: Infrastructure · Manufacturing & engineering, built in-house | C93: Paragraph | D93: In-house warehousing and packaging units protect finished goods and keep dispatch organised for domestic and export orders. | G93: New copy (not on WordPress)
A94: /about | B94: Infrastructure · Manufacturing & engineering, built in-house | C94: Subheading | D94: Domestic & export supply | G94: New copy (not on WordPress)
A95: /about | B95: Infrastructure · Manufacturing & engineering, built in-house | C95: Paragraph | D95: From our Ahmedabad facility we supply customers across India and export markets including China and Taiwan. | G95: New copy (not on WordPress)
A96: /about | B96: Infrastructure · Manufacturing & engineering, built in-house | C96: Paragraph | D96: Procurement · design · QC · warehousing · packaging | G96: New copy (not on WordPress)
A97: /about | B97: Infrastructure · Manufacturing & engineering, built in-house | C97: Paragraph | D97: 10,000+ sq ft at GIDC Kathwada, Ahmedabad | G97: New copy (not on WordPress)
A98: /about | B98: Infrastructure · Manufacturing & engineering, built in-house | C98: Paragraph | D98: Built under one roof | G98: New copy (not on WordPress)
A99: /about | B99: Infrastructure · Manufacturing & engineering, built in-house | C99: Paragraph | D99: China & Taiwan | G99: New copy (not on WordPress)
A100: /about | B100: Infrastructure · Manufacturing & engineering, built in-house | C100: Paragraph | D100: Explore our infrastructure → | G100: New copy (not on WordPress)
A101: /about | B101: What we believe · The values behind the work | C101: Heading | D101: The values behind the work | G101: New copy (not on WordPress)
... A131: /career | B131: Career · Build a career where ideas count | C131: Page title | D131: Build a career where ideas count | G131: New copy (not on WordPress)
A132: /career | B132: Career · Build a career where ideas count | C132: Paragraph | D132: There is always something happening at Philbrick that keeps the passion flowing. If that sounds like you, we would like to read your resume. | E132: Reworded from the WordPress page: Career | G132: Adapted from WordPress
A133: /career | B133: Career · Build a career where ideas count | C133: Paragraph | D133: Working at Philbrick Technologies (India) Pvt. Ltd. might seem anarchic at times, but it's never dreary. There is always something happening that keeps the passion flowing continually. The work is such, after all. It requires fervor that comes from inside and builds brands that endure. | E133: Same wording as the WordPress page: Career | G133: Matches WordPress
A134: /career | B134: Career · Build a career where ideas count | C134: Paragraph | D134: Philbrick Technologies (India) Pvt. Ltd. is not a single, person-centric company. It is a family where every person and his ideas are treated equally. We even undertake training programmes at various levels, so as to ensure that every employee works to the best of his or her capabilities. | E134: Same wording as the WordPress page: Career | G134: Matches WordPress
A135: /career | B135: Career · Build a career where ideas count | C135: Paragraph | D135: Mail your resume on | G135: New copy (not on WordPress)
A136: /career | B136: Career · Build a career where ideas count | C136: Link | D136: hr.philbrickindia@gmail.com | G136: New copy (not on WordPress)
A137: /career | B137: What we believe · The values behind the work | C137: Heading | D137: The values behind the work | G137: New copy (not on WordPress)
A138: /career | B138: What we believe · The values behind the work | C138: Paragraph | D138: The principles that guide how we design, build and support elevator components, and how we work with each other. | G138: New copy (not on WordPress)
A139: /career | B139: What we believe · The values behind the work | C139: Subheading | D139: Safety first | G139: New copy (not on WordPress)
A140: /career | B140: What we believe · The values behind the work | C140: Paragraph | D140: Elevators carry people. Products like the Automatic Rescue Device exist because passenger safety is the first requirement, never an afterthought. | G140: New copy (not on WordPress)
A141: /career | B141: What we believe · The values behind the work | C141: Subheading | D141: Engineer in-house | G141: New copy (not on WordPress)
A142: /career | B142: What we believe · The values behind the work | C142: Paragraph | D142: We design and build our control, door and signalling systems ourselves, so we understand them completely and can stand behind them. | G142: New copy (not on WordPress)
A143: /career | B143: What we believe · The values behind the work | C143: Subheading | D143: Consistent quality | G143: New copy (not on WordPress)
A144: /career | B144: What we believe · The values behind the work | C144: Paragraph | D144: Dedicated procurement, design and quality-control units keep fit, finish and function consistent from one batch to the next. | G144: New copy (not on WordPress)
A145: /career | B145: What we believe · The values behind the work | C145: Subheading | D145: Support the customer | G145: New copy (not on WordPress)
A146: /career | B146: What we believe · The values behind the work | C146: Paragraph | D146: From specification to after-sales, our team supports installers and building owners for the long life of the equipment. | G146: New copy (not on WordPress)
... A205: /downloads | B205: Let's build upward · Need a specific datasheet? | C205: Link | D205: Browse products | G205: New copy (not on WordPress)
A206: /infrastructure | B206: Page | C206: List item | D206: Home | E206: WordPress page was empty | G206: New copy (not on WordPress)
A207: /infrastructure | B207: Page | C207: List item | D207: Infrastructure | E207: WordPress page was empty | G207: New copy (not on WordPress)
A208: /infrastructure | B208: Capability · Built in-house, end to end | C208: Page title | D208: Built in-house, end to end | E208: WordPress page was empty | G208: New copy (not on WordPress)
A209: /infrastructure | B209: Capability · Built in-house, end to end | C209: Paragraph | D209: From procurement and design to manufacturing, quality control and dispatch, Philbrick controls every stage of the build at its Ahmedabad facility. | E209: WordPress page was empty | G209: New copy (not on WordPress)
A210: /infrastructure | B210: Capability · Built in-house, end to end | C210: Paragraph | D210: Doing the work ourselves is how we keep quality consistent. | E210: WordPress page was empty | G210: New copy (not on WordPress)
A211: /infrastructure | B211: Capability · Built in-house, end to end | C211: Paragraph | D211: Philbrick's Ahmedabad facility brings together dedicated units for procurement, design and R&D, manufacturing, quality control, warehousing and packaging. Controlling each stage, rather than outsourcing it, is what lets us hold fit, finish and function to a consistent standard, support both new installations and modernisation, and keep lead times in our own hands. | E211: WordPress page was empty | G211: New copy (not on WordPress)
A212: /infrastructure | B212: Infrastructure · Manufacturing & engineering, in-house | C212: Heading | D212: Manufacturing & engineering, in-house | E212: WordPress page was empty | G212: New copy (not on WordPress)
A213: /infrastructure | B213: Infrastructure · Manufacturing & engineering, in-house | C213: Paragraph | D213: The dedicated units behind every Philbrick product. | E213: WordPress page was empty | G213: New copy (not on WordPress)
A214: /infrastructure | B214: Infrastructure · Manufacturing & engineering, in-house | C214: Subheading | D214: In-house manufacturing | E214: WordPress page was empty | G214: New copy (not on WordPress)
A215: /infrastructure | B215: Infrastructure · Manufacturing & engineering, in-house | C215: Paragraph | D215: A well organised campus with 10,000+ sq feet of working area with latest manufacturing facilities and LAN connectivity, doubled in 2019 to meet growing market demand. | E215: Reworded from the WordPress page: Company | G215: Adapted from WordPress
A216: /infrastructure | B216: Infrastructure · Manufacturing & engineering, in-house | C216: Subheading | D216: Design & R&D | E216: WordPress page was empty | G216: New copy (not on WordPress)
A217: /infrastructure | B217: Infrastructure · Manufacturing & engineering, in-house | C217: Paragraph | D217: High tech equipped R&D infrastructure backed by Highly Qualified Engineers' team, skilled technicians and ERP, dedicated to developing control, door-operator, safety and display products. | E217: Reworded from the WordPress page: Company | G217: Adapted from WordPress
... A325: /news-events | B325: Let's build upward · Have a question in the meantime? | C325: Link | D325: Browse products | E325: WordPress page held demo text only (Lorem ipsum) | G325: Placeholder - needs client input
A326: /news-events/door-mechanism-assembly-line-upgrade | B326: Page | C326: List item | D326: Home | G326: Placeholder - needs client input
...

Sheet Product content
A1: Page URL | B1: Section | C1: Item type | D1: Current Website Text | E1: Suggested / WordPress Text | F1: Client Final Text | G1: Status
A2: /products/ard | B2: Page | C2: List item | D2: Home | G2: New copy (not on WordPress)
A3: /products/ard | B3: Page | C3: List item | D3: Products | G3: New copy (not on WordPress)
A4: /products/ard | B4: Page | C4: List item | D4: Automatic Rescue Device (ARD) | G4: New copy (not on WordPress)
A5: /products/ard | B5: Safety & Intelligence · Automatic Rescue Device (ARD) | C5: Page title | D5: Automatic Rescue Device (ARD) | G5: New copy (not on WordPress)
A6: /products/ard | B6: Safety & Intelligence · Automatic Rescue Device (ARD) | C6: Paragraph | D6: Nobody stays trapped. | G6: New copy (not on WordPress)
A7: /products/ard | B7: Safety & Intelligence · Automatic Rescue Device (ARD) | C7: Paragraph | D7: Lift Power LP440/LP220 is a specially designed High Starting Current type Inverter to operate the LIFT in Emergency Mode to rescue the passenger in power fail condition. When mains power fails, it automatically brings the elevator to the nearest landing on backup power and opens the doors so passengers are never left stranded between floors. | G7: New copy (not on WordPress)
A8: /products/ard | B8: Safety & Intelligence · Automatic Rescue Device (ARD) | C8: Subheading | D8: Salient Features | G8: New copy (not on WordPress)
A9: /products/ard | B9: Safety & Intelligence · Automatic Rescue Device (ARD) | C9: List item | D9: Suitable for Auto Door / Manual Door Lift. | G9: New copy (not on WordPress)
A10: /products/ard | B10: Safety & Intelligence · Automatic Rescue Device (ARD) | C10: List item | D10: High Starting Current for High Starting Torque Requirement. | E10: Same wording as the WordPress product: ARD (Automatic Rescue Device) | G10: Matches WordPress
A11: /products/ard | B11: Safety & Intelligence · Automatic Rescue Device (ARD) | C11: List item | D11: Automatic Shut Down to prevent unnecessary Battery Usage. | E11: Same wording as the WordPress product: ARD (Automatic Rescue Device) | G11: Matches WordPress
A12: /products/ard | B12: Safety & Intelligence · Automatic Rescue Device (ARD) | C12: List item | D12: Digital Signal processing for Pure Sinewave output with Power Efficient Low On-Resistance Easy based design. | E12: Same wording as the WordPress product: ARD (Automatic Rescue Device) | G12: Matches WordPress
A13: /products/ard | B13: Safety & Intelligence · Automatic Rescue Device (ARD) | C13: List item | D13: IGBT based charging for longer battery life. | E13: Same wording as the WordPress product: ARD (Automatic Rescue Device) | G13: Matches WordPress
A14: /products/ard | B14: Safety & Intelligence · Automatic Rescue Device (ARD) | C14: List item | D14: Automatic Battery Charging Cut off. | G14: New copy (not on WordPress)
A15: /products/ard | B15: Safety & Intelligence · Automatic Rescue Device (ARD) | C15: List item | D15: Protection against deep discharge of Battery. | E15: Same wording as the WordPress product: ARD (Automatic Rescue Device) | G15: Matches WordPress
A16: /products/ard | B16: Safety & Intelligence · Automatic Rescue Device (ARD) | C16: List item | D16: Status indication on LCD / LEDs. | G16: New copy (not on WordPress)
A17: /products/ard | B17: Safety & Intelligence · Automatic Rescue Device (ARD) | C17: List item | D17: Available up to 30 H.P. Motor Rating. | G17: New copy (not on WordPress)
A18: /products/ard | B18: Safety & Intelligence · Automatic Rescue Device (ARD) | C18: Subheading | D18: Models and specifications | G18: New copy (not on WordPress)
A19: /products/ard | B19: Safety & Intelligence · Automatic Rescue Device (ARD) | C19: Subheading | D19: Automatic Rescue Device (ARD) for Lift | G19: New copy (not on WordPress)
A20: /products/ard | B20: Safety & Intelligence · Automatic Rescue Device (ARD) | C20: Paragraph | D20: Lift Power LP440/ LP220 is application specially designed High Starting Current type Inverter to operate the LIFT in Emergency Mode to rescue the passenger in Power fail condition. | E20: Same wording as the WordPress product: ARD (Automatic Rescue Device) | G20: Matches WordPress
A21: /products/ard | B21: Let's build upward · Interested in Automatic Rescue Device (ARD)? | C21: Heading | D21: Interested in Automatic Rescue Device (ARD)? | G21: New copy (not on WordPress)
A22: /products/ard | B22: Let's build upward · Interested in Automatic Rescue Device (ARD)? | C22: Paragraph | D22: Tell us about your project and the Philbrick team will help you specify the right solution. | G22: New copy (not on WordPress)
A23: /products/ard | B23: Let's build upward · Interested in Automatic Rescue Device (ARD)? | C23: Link | D23: Request a quote | G23: New copy (not on WordPress)
A24: /products/ard | B24: Let's build upward · Interested in Automatic Rescue Device (ARD)? | C24: Link | D24: All products | G24: New copy (not on WordPress)
A25: /products/cop-lop | B25: Page | C25: List item | D25: Home | G25: New copy (not on WordPress)
A26: /products/cop-lop | B26: Page | C26: List item | D26: Products | G26: New copy (not on WordPress)
A27: /products/cop-lop | B27: Page | C27: List item | D27: COP / LOP | G27: New copy (not on WordPress)
A28: /products/cop-lop | B28: Cabin & Fixtures · COP / LOP | C28: Page title | D28: COP / LOP | G28: New copy (not on WordPress)
A29: /products/cop-lop | B29: Cabin & Fixtures · COP / LOP | C29: Paragraph | D29: The passenger interface. | G29: New copy (not on WordPress)
A30: /products/cop-lop | B30: Cabin & Fixtures · COP / LOP | C30: Paragraph | D30: The Car Operating Panel (COP) and Landing Operating Panel (LOP) are how passengers interact with the elevator. Philbrick builds them in hard-wearing finishes with tactile buttons and clear indication, so calling and commanding the lift is intuitive at the landing and inside the car. | G30: New copy (not on WordPress)
A31: /products/cop-lop | B31: Let's build upward · Interested in COP / LOP? | C31: Heading | D31: Interested in COP / LOP? | G31: New copy (not on WordPress)
A32: /products/cop-lop | B32: Let's build upward · Interested in COP / LOP? | C32: Paragraph | D32: Tell us about your project and the Philbrick team will help you specify the right solution. | G32: New copy (not on WordPress)
... A42: /products/elevator-cabin | B42: Titanium Gold Designed with Stainless Steel with Finish Car | C42: Subheading | D42: Salient Features | G42: New copy (not on WordPress)
A43: /products/elevator-cabin | B43: Titanium Gold Designed with Stainless Steel with Finish Car | C43: List item | D43: Homogeneous Bottom & Top Structure with minimum welding joints. | E43: Same wording as the WordPress product: Titanium Gold Designed with Stainless Steel with Finish Car | G43: Matches WordPress
A44: /products/elevator-cabin | B44: Titanium Gold Designed with Stainless Steel with Finish Car | C44: List item | D44: Available in MS Powder Coated / Galvanized Powder Coated and Stainless Steel Material. | E44: Same wording as the WordPress page: Philbrick India | G44: Matches WordPress
A45: /products/elevator-cabin | B45: Titanium Gold Designed with Stainless Steel with Finish Car | C45: List item | D45: Customized Design of Various combination of Plain S. S., Designer S. S. Sheet Material, MS Powder Coated, etc. | E45: Same wording as the WordPress page: Philbrick India | G45: Matches WordPress
A46: /products/elevator-cabin | B46: Stainless Steel with Mirror Finish Car | C46: Heading | D46: Stainless Steel with Mirror Finish Car | G46: New copy (not on WordPress)
A47: /products/elevator-cabin | B47: Stainless Steel with Mirror Finish Car | C47: Subheading | D47: Salient Features | G47: New copy (not on WordPress)
A48: /products/elevator-cabin | B48: Stainless Steel with Mirror Finish Car | C48: List item | D48: Homogeneous Bottom & Top Structure with minimum welding joints. | E48: Same wording as the WordPress product: Titanium Gold Designed with Stainless Steel with Finish Car | G48: Matches WordPress
A49: /products/elevator-cabin | B49: Stainless Steel with Mirror Finish Car | C49: List item | D49: Available in MS Powder Coated / Galvanized Powder Coated and Stainless Steel Material. | E49: Same wording as the WordPress page: Philbrick India | G49: Matches WordPress
A50: /products/elevator-cabin | B50: Stainless Steel with Mirror Finish Car | C50: List item | D50: Customized Design of Various combination of Plain S. S., Designer S. S. Sheet Material, MS Powder Coated, etc. | E50: Same wording as the WordPress page: Philbrick India | G50: Matches WordPress
A51: /products/elevator-cabin | B51: Stainless Steel with M S Coated Car | C51: Heading | D51: Stainless Steel with M S Coated Car | G51: New copy (not on WordPress)
A52: /products/elevator-cabin | B52: Stainless Steel with M S Coated Car | C52: Subheading | D52: Salient Features | G52: New copy (not on WordPress)
A53: /products/elevator-cabin | B53: Stainless Steel with M S Coated Car | C53: List item | D53: Homogeneous Bottom & Top Structure with minimum welding joints. | E53: Same wording as the WordPress product: Titanium Gold Designed with Stainless Steel with Finish Car | G53: Matches WordPress
A54: /products/elevator-cabin | B54: Stainless Steel with M S Coated Car | C54: List item | D54: Available in MS Powder Coated / Galvanized Powder Coated and Stainless Steel Material. | E54: Same wording as the WordPress page: Philbrick India | G54: Matches WordPress
A55: /products/elevator-cabin | B55: Stainless Steel with M S Coated Car | C55: List item | D55: Customized Design of Various combination of Plain S. S., Designer S. S. Sheet Material, MS Powder Coated, etc. | E55: Same wording as the WordPress page: Philbrick India | G55: Matches WordPress
A56: /products/elevator-cabin | B56: Elevator Cabin (Full Glass Capsule Car Square) | C56: Heading | D56: Elevator Cabin (Full Glass Capsule Car Square) | G56: New copy (not on WordPress)
A57: /products/elevator-cabin | B57: Elevator Cabin (Full Glass Capsule Car Square) | C57: Subheading | D57: Salient Features | G57: New copy (not on WordPress)
A58: /products/elevator-cabin | B58: Elevator Cabin (Full Glass Capsule Car Square) | C58: List item | D58: Homogeneous Bottom & Top Structure with minimum welding joints. | E58: Same wording as the WordPress product: Titanium Gold Designed with Stainless Steel with Finish Car | G58: Matches WordPress
A59: /products/elevator-cabin | B59: Elevator Cabin (Full Glass Capsule Car Square) | C59: List item | D59: Available in MS Powder Coated / Galvanized Powder Coated and Stainless Steel Material. | E59: Same wording as the WordPress page: Philbrick India | G59: Matches WordPress
A60: /products/elevator-cabin | B60: Elevator Cabin (Full Glass Capsule Car Square) | C60: List item | D60: Customized Design of Various combination of Plain S. S., Designer S. S. Sheet Material, MS Powder Coated, etc. | E60: Same wording as the WordPress page: Philbrick India | G60: Matches WordPress
A61: /products/elevator-cabin | B61: Let's build upward · Interested in Elevator Cabin? | C61: Heading | D61: Interested in Elevator Cabin? | G61: New copy (not on WordPress)
A62: /products/elevator-cabin | B62: Let's build upward · Interested in Elevator Cabin? | C62: Paragraph | D62: Tell us about your project and the Philbrick team will help you specify the right solution. | G62: New copy (not on WordPress)
A63: /products/elevator-cabin | B63: Let's build upward · Interested in Elevator Cabin? | C63: Link | D63: Request a quote | G63: New copy (not on WordPress)
A64: /products/elevator-cabin | B64: Let's build upward · Interested in Elevator Cabin? | C64: Link | D64: All products | G64: New copy (not on WordPress)
A65: /products/elevator-control-panel | B65: Page | C65: List item | D65: Home | G65: New copy (not on WordPress)
A66: /products/elevator-control-panel | B66: Page | C66: List item | D66: Products | G66: New copy (not on WordPress)
A67: /products/elevator-control-panel | B67: Page | C67: List item | D67: Elevator Control Panel | G67: New copy (not on WordPress)
A68: /products/elevator-control-panel | B68: Control & Drives · Elevator Control Panel | C68: Page title | D68: Elevator Control Panel | G68: New copy (not on WordPress)
A69: /products/elevator-control-panel | B69: Control & Drives · Elevator Control Panel | C69: Paragraph | D69: The brain of every ride. | G69: New copy (not on WordPress)
A70: /products/elevator-control-panel | B70: Overview · The brain of every ride. | C70: Heading | D70: The brain of every ride. | G70: New copy (not on WordPress)
A71: /products/elevator-control-panel | B71: Overview · The brain of every ride. | C71: Paragraph | D71: The elevator control panel is the intelligence behind the ride: it drives the machine, levels the car, sequences the doors and supervises every safety circuit. Philbrick builds control panels in-house using RISC microprocessor-based High Speed clocked design for automatic-door, manual-door and hydraulic elevators. Features include Multi Functional keypad with LCD display, Programmable configuration, Self Diagnostic/Debugging Mode, Opto Coupler based Galvanic Isolation for all Inputs and Outputs, and PTC protected Digital I/O. | G71: New copy (not on WordPress)
A72: /products/elevator-control-panel | B72: Overview · The brain of every ride. | C72: List item | D72: RISC microprocessor-based High Speed design | G72: New copy (not on WordPress)
A73: /products/elevator-control-panel | B73: Overview · The brain of every ride. | C73: List item | D73: Automatic, manual and hydraulic variants | G73: New copy (not on WordPress)
A74: /products/elevator-control-panel | B74: Overview · The brain of every ride. | C74: List item | D74: Self Diagnostic/Debugging Mode for onsite troubleshooting | E74: Same wording as the WordPress page: Philbrick India | G74: Matches WordPress
A75: /products/elevator-control-panel | B75: Overview · The brain of every ride. | C75: List item | D75: Opto Coupler based Galvanic Isolation | G75: New copy (not on WordPress)
A76: /products/elevator-control-panel | B76: The range · Explore Elevator Control Panel | C76: Heading | D76: Explore Elevator Control Panel | G76: New copy (not on WordPress)
A77: /products/elevator-control-panel | B77: The range · Explore Elevator Control Panel | C77: Paragraph | D77: Choose the elevator control panel variant that fits your project. The Philbrick team will help you specify the rest. | G77: New copy (not on WordPress)
A78: /products/elevator-control-panel | B78: The range · Explore Elevator Control Panel | C78: Link | D78: Elevator Control Panel Automatic Door Controller Xpert Main Board based Auto Door V3F Type Control Panel available in 8, 12 and 16 landing floor configurations with Full Collective Logic. Options include customized MRL enclosure, ARD functionality and control panel for Synchronous Motor (Gearless Machine). | E78: Reworded from the WordPress product: Automatic Door Controller | G78: Adapted from WordPress
A79: /products/elevator-control-panel | B79: The range · Explore Elevator Control Panel | C79: Link | D79: Elevator Control Panel Manual Door Controller Available in V3F Drive and Single Speed variants with Elevat+ and Xpert Main Board options. V3F panels in 8 to 16 landing configurations with Down/Full Collective Logic. Options include customized MRL enclosure, ARD functionality, Phase Sequence Corrector and Synchronous Motor control. | E79: Reworded from the WordPress product: Manual Door Controller | G79: Adapted from WordPress
A80: /products/elevator-control-panel | B80: The range · Explore Elevator Control Panel | C80: Link | D80: Elevator Control Panel Hydraulic Controller Xpert and Elevat+ Main Board based Hydraulic Lift Control Panels for up to 8 landing floors, available for Automatic and Manual Door configurations. Options include DOL/Star-Delta Main Pump Starter, MRL application, Phase Sequence Corrector and Front & Rear Door operation. | E80: Reworded from the WordPress product: Hydraulic Controller | G80: Adapted from WordPress
A81: /products/elevator-control-panel | B81: Let's build upward · Interested in Elevator Control Panel? | C81: Heading | D81: Interested in Elevator Control Panel? | G81: New copy (not on WordPress)
A82: /products/elevator-control-panel | B82: Let's build upward · Interested in Elevator Control Panel? | C82: Paragraph | D82: Tell us about your project and the Philbrick team will help you specify the right solution. | G82: New copy (not on WordPress)
A83: /products/elevator-control-panel | B83: Let's build upward · Interested in Elevator Control Panel? | C83: Link | D83: Request a quote | G83: New copy (not on WordPress)
A84: /products/elevator-control-panel | B84: Let's build upward · Interested in Elevator Control Panel? | C84: Link | D84: All products | G84: New copy (not on WordPress)
A85: /products/elevator-control-panel/automatic-door-controller | B85: Page | C85: List item | D85: Home | G85: New copy (not on WordPress)
A86: /products/elevator-control-panel/automatic-door-controller | B86: Page | C86: List item | D86: Products | G86: New copy (not on WordPress)
A87: /products/elevator-control-panel/automatic-door-controller | B87: Page | C87: List item | D87: Elevator Control Panel | G87: New copy (not on WordPress)
A88: /products/elevator-control-panel/automatic-door-controller | B88: Page | C88: List item | D88: Automatic Door Controller | G88: New copy (not on WordPress)
A89: /products/elevator-control-panel/automatic-door-controller | B89: Elevator Control Panel · Automatic Door Controller | C89: Page title | D89: Automatic Door Controller | G89: New copy (not on WordPress)
A90: /products/elevator-control-panel/automatic-door-controller | B90: Elevator Control Panel · Automatic Door Controller | C90: Paragraph | D90: Xpert Main Board based Auto Door V3F Type Control Panel available in 8, 12 and 16 landing floor configurations with Full Collective Logic. Options include customized MRL enclosure, ARD functionality and control panel for Synchronous Motor (Gearless Machine). | E90: Reworded from the WordPress product: Automatic Door Controller | G90: Adapted from WordPress
A91: /products/elevator-control-panel/automatic-door-controller | B91: Elevator Control Panel · Automatic Door Controller | C91: Subheading | D91: Salient Features | G91: New copy (not on WordPress)
A92: /products/elevator-control-panel/automatic-door-controller | B92: Elevator Control Panel · Automatic Door Controller | C92: List item | D92: 16 Bit/ 32 Bit RISC microprocessor-based High Speed clocked design which enhance the processing speed for better elevator control. | E92: Same wording as the WordPress page: Philbrick India | G92: Matches WordPress
A93: /products/elevator-control-panel/automatic-door-controller | B93: Elevator Control Panel · Automatic Door Controller | C93: List item | D93: Multi Functional keypad with LCD 20 * 4 line display. | E93: Same wording as the WordPress page: Philbrick India | G93: Matches WordPress
A94: /products/elevator-control-panel/automatic-door-controller | B94: Elevator Control Panel · Automatic Door Controller | C94: List item | D94: Programmable configuration & Functionality makes flexible controlling. | E94: Same wording as the WordPress product: Automatic Door Controller | G94: Matches WordPress
A95: /products/elevator-control-panel/automatic-door-controller | B95: Elevator Control Panel · Automatic Door Controller | C95: List item | D95: Programmable Number of Floors, Floor Designation like B, P, C, L-1, -2, etc, Fireman floor, Home Landing Floor, Door Timings, Front & Rear Door Operation etc. | E95: Same wording as the WordPress page: Philbrick India | G95: Matches WordPress
A96: /products/elevator-control-panel/automatic-door-controller | B96: Elevator Control Panel · Automatic Door Controller | C96: List item | D96: Non Stop, VIP Mode & HALT Functionality. | G96: New copy (not on WordPress)
A97: /products/elevator-control-panel/automatic-door-controller | B97: Elevator Control Panel · Automatic Door Controller | C97: List item | D97: Password protected trip setting. | G97: New copy (not on WordPress)
A98: /products/elevator-control-panel/automatic-door-controller | B98: Elevator Control Panel · Automatic Door Controller | C98: List item | D98: Self Diagnostic/ Debugging Mode for Onsite troubleshooting. | E98: Same wording as the WordPress page: Philbrick India | G98: Matches WordPress
A99: /products/elevator-control-panel/automatic-door-controller | B99: Elevator Control Panel · Automatic Door Controller | C99: List item | D99: Auto FAN/ LIGHT functionality to save energy. | E99: Same wording as the WordPress page: Philbrick India | G99: Matches WordPress
A100: /products/elevator-control-panel/automatic-door-controller | B100: Elevator Control Panel · Automatic Door Controller | C100: List item | D100: Intelligent electronics STOP function. | G100: New copy (not on WordPress)
A101: /products/elevator-control-panel/automatic-door-controller | B101: Elevator Control Panel · Automatic Door Controller | C101: List item | D101: Auto/ Attendant Mode. | G101: New copy (not on WordPress)
A102: /products/elevator-control-panel/automatic-door-controller | B102: Elevator Control Panel · Automatic Door Controller | C102: List item | D102: Audio Buzzer O/P for Open Door condition in Manual Door. | E102: Same wording as the WordPress page: Philbrick India | G102: Matches WordPress
A103: /products/elevator-control-panel/automatic-door-controller | B103: Elevator Control Panel · Automatic Door Controller | C103: List item | D103: Call Buzzer O/P for Landing Floor Call prompting. | E103: Same wording as the WordPress page: Philbrick India | G103: Matches WordPress
A104: /products/elevator-control-panel/automatic-door-controller | B104: Elevator Control Panel · Automatic Door Controller | C104: List item | D104: Opto Coupler based Galvanic Isolation for all Inputs & Outputs. | E104: Same wording as the WordPress product: Automatic Door Controller | G104: Matches WordPress
A105: /products/elevator-control-panel/automatic-door-controller | B105: Elevator Control Panel · Automatic Door Controller | C105: List item | D105: Separate LED Indication for all Inputs & Outputs. | E105: Same wording as the WordPress product: Automatic Door Controller | G105: Matches WordPress
A106: /products/elevator-control-panel/automatic-door-controller | B106: Elevator Control Panel · Automatic Door Controller | C106: List item | D106: Hardware & Digital Filtering in all the input to suppress effects of Electrical Noise. | E106: Same wording as the WordPress product: Automatic Door Controller | G106: Matches WordPress
A107: /products/elevator-control-panel/automatic-door-controller | B107: Elevator Control Panel · Automatic Door Controller | C107: List item | D107: PTC protected all the Digital I/O to avoid failure due to field faults. | E107: Same wording as the WordPress page: Philbrick India | G107: Matches WordPress
A108: /products/elevator-control-panel/automatic-door-controller | B108: Elevator Control Panel · Automatic Door Controller | C108: List item | D108: Solid State Display Driver with Resettable Fuse protection. | E108: Same wording as the WordPress page: Philbrick India | G108: Matches WordPress
A109: /products/elevator-control-panel/automatic-door-controller | B109: Elevator Control Panel · Automatic Door Controller | C109: List item | D109: Faster learning & simple maintenance. | G109: New copy (not on WordPress)
...

Sheet Global elements
A1: Page URL | B1: Section | C1: Item type | D1: Current Website Text | E1: Suggested / WordPress Text | F1: Client Final Text | G1: Status
A2: All pages | B2: Header | C2: Logo wordmark | D2: Philbrick | E2: Philbrick India (WordPress site title) | G2: Matches WordPress
A3: All pages | B3: Header | C3: Tagline | D3: Providing Elevator Solutions | E3: Providing Elevator Solutions | G3: Matches WordPress
A4: All pages | B4: Header | C4: Navigation | D4: Home · About · Products · Infrastructure · Network · News & Events · Contact Us | E4: Same 7 items as the WordPress top menu | G4: Matches WordPress
A5: All pages | B5: Header | C5: Primary button | D5: Get a quote | G5: New copy (not on WordPress)
A6: All pages | B6: Footer | C6: Legal name | D6: Philbrick Technologies (India) Pvt. Ltd. | E6: PHILBRICK TECHNOLOGIES (INDIA) PVT. LTD. ALL RIGHTS RESERVED. | G6: Matches WordPress
A7: All pages | B7: Footer | C7: Helpline | D7: +91 84012 19941 | E7: Helpline: +91 840 121 9941 | G7: Matches WordPress
A8: All pages | B8: Footer | C8: WhatsApp line | D8: +91 99789 86631 | E8: +91 99789 86631 OR Chat On | G8: Matches WordPress
A9: All pages | B9: Footer | C9: Office line | D9: +91 93740 22660 | E9: +91 93740 22660 | G9: Matches WordPress
A10: All pages | B10: Footer | C10: Office line | D10: +91 98250 09420 | E10: +91 98250 09420 | G10: Matches WordPress
A11: All pages | B11: Footer | C11: Office line | D11: +91 99789 86635 | E11: +91 99789 86635 | G11: Matches WordPress
A12: All pages | B12: Footer | C12: Office hours | D12: Mon to Fri, 09:00 to 18:00 | E12: Mon-Fri 9:00 to 18:00 | G12: Matches WordPress
A13: All pages | B13: Footer | C13: Sales email | D13: sales@philbrickindia.com | E13: sales@philbrickindia.com | G13: Matches WordPress
A14: All pages | B14: Footer | C14: General email | D14: philbrick@philbrickindia.com | E14: philbrick@philbrickindia.com | G14: Matches WordPress
A15: All pages | B15: Footer | C15: Careers email | D15: hr.philbrickindia@gmail.com | E15: hr.philbrickindia@gmail.com (Career page) | G15: Matches WordPress
A16: All pages | B16: Footer | C16: Alternate email | D16: philbrick_controls@yahoo.com | E16: philbrick_controls@yahoo.com | G16: Matches WordPress
A17: All pages | B17: Footer | C17: Registered address | D17: Plot No. 69, Road No. 6, G.I.D.C. Kathwada, Ahmedabad 382430, Gujarat | E17: Plot No. 69, Road No. 6, G.I.D.C. Kathwada, Ahmedabad 382 430 India. | G17: Matches WordPress
A18: All pages | B18: Footer | C18: GST number | D18: 24AAHCP6212D1ZU | G18: Statistic - confirm with client
A19: All pages | B19: Footer | C19: CIN | D19: U31501GJ2014PTC078837 | G19: Statistic - confirm with client
A20: All pages | B20: Footer | C20: IEC | D20: 0814002951 | G20: Statistic - confirm with client
A21: All pages | B21: Footer | C21: WhatsApp link | D21: https://api.whatsapp.com/send?phone=+919978986631 | E21: Same link as the WordPress footer | G21: Matches WordPress
A22: All pages | B22: Footer | C22: Facebook | D22: https://www.facebook.com/philbrick.india | E22: https://www.facebook.com/philbrick.india | G22: Matches WordPress
A23: All pages | B23: Footer | C23: Instagram | D23: https://www.instagram.com/philbrick.india/ | E23: https://www.instagram.com/philbrick.india/ | G23: Matches WordPress
A24: All pages | B24: Footer | C24: X (formerly Twitter) | D24: https://twitter.com/SaranshPatel20 | E24: https://twitter.com/SaranshPatel20 | G24: Matches WordPress
A25: All pages | B25: Footer | C25: Newsletter heading | D25: Stay updated | G25: New copy (not on WordPress)
A26: All pages | B26: Footer | C26: Newsletter note | D26: Quarterly. No spam. | G26: New copy (not on WordPress)
A27: All pages | B27: Live chat | C27: Tawk.to property | D27: 6039cf23385de407571a9744 / 1evgt29n1 | E27: Same property as the WordPress plugin | G27: Matches WordPress
A28: All pages | B28: Named contact | C28: Customer Relationship (CRM) | D28: Saransh Patel | G28: Confirm with client
A29: All pages | B29: Named contact | C29: Technical Support | D29: Prakash Patel | G29: Confirm with client
A30: All pages | B30: Leadership | C30: Founder & Mentor | D30: Vasant Patel | G30: Confirm with client
A31: All pages | B31: Leadership | C31: Chief Executive Officer | D31: Saransh Patel | G31: Confirm with client

Sheet SEO & meta
A1: Page URL | B1: Section | C1: Item type | D1: Current Website Text | E1: Suggested / WordPress Text | F1: Client Final Text | G1: Notes
A2: / | B2: SEO | C2: Browser / search title | D2: Philbrick | Providing Elevator Solutions | G2: Shown in the browser tab and Google results
A3: / | B3: SEO | C3: Meta description | D3: Philbrick Technologies is an Ahmedabad-based manufacturer, exporter and supplier of elevator control panels, integrated controllers, automatic rescue devices, door operators, cabins, displays and complete elevator components. | G3: Google result snippet, aim for 150-160 characters
A4: /about | B4: SEO | C4: Browser / search title | D4: About Us · Philbrick | G4: Shown in the browser tab and Google results
A5: /about | B5: SEO | C5: Meta description | D5: Philbrick Controls India was founded in 1992 in Ahmedabad with a main focus on providing automation solutions by R&D and production of Control Instruments, Control Panels and elevator accessories. | G5: Google result snippet, aim for 150-160 characters
A6: /about | B6: SEO | C6: Social share description | D6: Philbrick Technologies is an Ahmedabad-based manufacturer, exporter and supplier of elevator control panels, integrated controllers, automatic rescue devices, door operators, cabins, displays and complete elevator components.
A7: /career | B7: SEO | C7: Browser / search title | D7: Career · Philbrick | G7: Shown in the browser tab and Google results
A8: /career | B8: SEO | C8: Meta description | D8: Work at Philbrick Technologies (India) Pvt. Ltd. in Ahmedabad. A family where every person and their ideas are treated equally, with training programmes at various levels. | G8: Google result snippet, aim for 150-160 characters
A9: /career | B9: SEO | C9: Social share description | D9: Philbrick Technologies is an Ahmedabad-based manufacturer, exporter and supplier of elevator control panels, integrated controllers, automatic rescue devices, door operators, cabins, displays and complete elevator components.
A10: /contact | B10: SEO | C10: Browser / search title | D10: Contact · Philbrick | G10: Shown in the browser tab and Google results
A11: /contact | B11: SEO | C11: Meta description | D11: Talk to Philbrick Technologies about elevator control panels, ARD, door operators, cabins, displays and components. Based in Ahmedabad, Gujarat. | G11: Google result snippet, aim for 150-160 characters
A12: /contact | B12: SEO | C12: Social share description | D12: Philbrick Technologies is an Ahmedabad-based manufacturer, exporter and supplier of elevator control panels, integrated controllers, automatic rescue devices, door operators, cabins, displays and complete elevator components.
A13: /downloads | B13: SEO | C13: Browser / search title | D13: Downloads · Philbrick | G13: Shown in the browser tab and Google results
A14: /downloads | B14: SEO | C14: Meta description | D14: Product brochures and catalogues from Philbrick Technologies, including the STEP brochure for the integrated elevator controller range. | G14: Google result snippet, aim for 150-160 characters
A15: /downloads | B15: SEO | C15: Social share description | D15: Philbrick Technologies is an Ahmedabad-based manufacturer, exporter and supplier of elevator control panels, integrated controllers, automatic rescue devices, door operators, cabins, displays and complete elevator components.
A16: /infrastructure | B16: SEO | C16: Browser / search title | D16: Infrastructure · Philbrick | G16: Shown in the browser tab and Google results
A17: /infrastructure | B17: SEO | C17: Meta description | D17: Philbrick's in-house infrastructure: manufacturing, design & R&D, quality control, procurement and warehousing at our Ahmedabad facility. | G17: Google result snippet, aim for 150-160 characters
A18: /infrastructure | B18: SEO | C18: Social share description | D18: Philbrick Technologies is an Ahmedabad-based manufacturer, exporter and supplier of elevator control panels, integrated controllers, automatic rescue devices, door operators, cabins, displays and complete elevator components.
A19: /manifest.webmanifest | B19: SEO | C19: Browser / search title | G19: Shown in the browser tab and Google results
A20: /manifest.webmanifest | B20: SEO | C20: Meta description | G20: Google result snippet, aim for 150-160 characters
A21: /milestone | B21: SEO | C21: Browser / search title | D21: Milestone & Awards · Philbrick | G21: Shown in the browser tab and Google results
A22: /milestone | B22: SEO | C22: Meta description | D22: Key milestones in Philbrick Technologies' journey since 1992: from founding in Ahmedabad to a complete elevator-component range. | G22: Google result snippet, aim for 150-160 characters
A23: /milestone | B23: SEO | C23: Social share description | D23: Philbrick Technologies is an Ahmedabad-based manufacturer, exporter and supplier of elevator control panels, integrated controllers, automatic rescue devices, door operators, cabins, displays and complete elevator components.
A24: /network | B24: SEO | C24: Browser / search title | D24: Network · Philbrick | G24: Shown in the browser tab and Google results
A25: /network | B25: SEO | C25: Meta description | D25: Philbrick's reach: based in Ahmedabad, supplying elevator components across India and exporting to markets including China and Taiwan. | G25: Google result snippet, aim for 150-160 characters
A26: /network | B26: SEO | C26: Social share description | D26: Philbrick Technologies is an Ahmedabad-based manufacturer, exporter and supplier of elevator control panels, integrated controllers, automatic rescue devices, door operators, cabins, displays and complete elevator components.
A27: /news-events | B27: SEO | C27: Browser / search title | D27: News & Events · Philbrick | G27: Shown in the browser tab and Google results
A28: /news-events | B28: SEO | C28: Meta description | D28: News, product updates and events from Philbrick Technologies. Check back for the latest from our Ahmedabad facility. | G28: Google result snippet, aim for 150-160 characters
A29: /news-events | B29: SEO | C29: Social share description | D29: Philbrick Technologies is an Ahmedabad-based manufacturer, exporter and supplier of elevator control panels, integrated controllers, automatic rescue devices, door operators, cabins, displays and complete elevator components.
A30: /news-events/door-mechanism-assembly-line-upgrade | B30: SEO | C30: Browser / search title | D30: Door-mechanism assembly line upgraded · Philbrick | G30: Shown in the browser tab and Google results
A31: /news-events/door-mechanism-assembly-line-upgrade | B31: SEO | C31: Meta description | D31: An upgrade to our Synergy auto door assembly line improves consistency and throughput at the Ahmedabad facility. | G31: Google result snippet, aim for 150-160 characters
A32: /news-events/growing-our-component-supply-network | B32: SEO | C32: Browser / search title | D32: Growing our component supply network · Philbrick | G32: Shown in the browser tab and Google results
A33: /news-events/growing-our-component-supply-network | B33: SEO | C33: Meta description | D33: We continue to expand how we reach installers and OEMs across India and our export markets with single-source component supply. | G33: Google result snippet, aim for 150-160 characters
A34: /news-events/installer-training-program-control-safety | B34: SEO | C34: Browser / search title | D34: Installer training program for control and safety systems · Philbrick | G34: Shown in the browser tab and Google results
A35: /news-events/installer-training-program-control-safety | B35: SEO | C35: Meta description | D35: A hands-on session for installer partners covering panel commissioning, ARD setup and door-operator tuning. | G35: Google result snippet, aim for 150-160 characters
A36: /news-events/philbrick-at-india-elevator-technology-expo | B36: SEO | C36: Browser / search title | D36: Philbrick at the India elevator technology expo · Philbrick | G36: Shown in the browser tab and Google results
A37: /news-events/philbrick-at-india-elevator-technology-expo | B37: SEO | C37: Meta description | D37: Meet the team and see our control panels, ARD and Synergy auto doors on display at an upcoming vertical-transport exhibition. | G37: Google result snippet, aim for 150-160 characters
A38: /news-events/serial-can-bus-control-panel-in-production | B38: SEO | C38: Browser / search title | D38: Serial CAN bus control panel enters full production · Philbrick | G38: Shown in the browser tab and Google results
A39: /news-events/serial-can-bus-control-panel-in-production | B39: SEO | C39: Meta description | D39: Our serial CAN bus integrated control panel moves to full in-house production, cutting wiring and installation time for mid-rise elevators. | G39: Google result snippet, aim for 150-160 characters
A40: /news-events/why-every-lift-benefits-from-ard | B40: SEO | C40: Browser / search title | D40: Why every lift benefits from an Automatic Rescue Device · Philbrick | G40: Shown in the browser tab and Google results
A41: /news-events/why-every-lift-benefits-from-ard | B41: SEO | C41: Meta description | D41: A short explainer on how the ARD safely brings a car to the nearest floor during a power failure, and why it matters. | G41: Google result snippet, aim for 150-160 characters
... A43: /privacy-policy | B43: SEO | C43: Meta description | D43: How Philbrick Technologies India Pvt Limited collects, uses, retains and protects the personal data you submit through this website. | G43: Google result snippet, aim for 150-160 characters
A44: /privacy-policy | B44: SEO | C44: Social share description | D44: Philbrick Technologies is an Ahmedabad-based manufacturer, exporter and supplier of elevator control panels, integrated controllers, automatic rescue devices, door operators, cabins, displays and complete elevator components.
A45: /products | B45: SEO | C45: Browser / search title | D45: Products · Philbrick | G45: Shown in the browser tab and Google results
A46: /products | B46: SEO | C46: Meta description | D46: Explore Philbrick's elevator component range: control panels, integrated controllers, ARD, door operators, Synergy auto doors, cabins, displays, COP/LOP and voice systems. | G46: Google result snippet, aim for 150-160 characters
A47: /products | B47: SEO | C47: Social share description | D47: Philbrick Technologies is an Ahmedabad-based manufacturer, exporter and supplier of elevator control panels, integrated controllers, automatic rescue devices, door operators, cabins, displays and complete elevator components.
A48: /products/ard | B48: SEO | C48: Browser / search title | D48: Automatic Rescue Device (ARD) · Philbrick | G48: Shown in the browser tab and Google results
A49: /products/ard | B49: SEO | C49: Meta description | D49: On a power failure the Automatic Rescue Device moves the car to the nearest floor and opens the doors, releasing passengers safely. A core Philbrick safety product. | G49: Google result snippet, aim for 150-160 characters
A50: /products/cop-lop | B50: SEO | C50: Browser / search title | D50: COP / LOP · Philbrick | G50: Shown in the browser tab and Google results
A51: /products/cop-lop | B51: SEO | C51: Meta description | D51: Car Operating Panels and Landing Operating Panels: the buttons and indicators passengers use to call and command the lift, in durable finishes with clear signalling. | G51: Google result snippet, aim for 150-160 characters
A52: /products/elevator-cabin | B52: SEO | C52: Browser / search title | D52: Elevator Cabin · Philbrick | G52: Shown in the browser tab and Google results
A53: /products/elevator-cabin | B53: SEO | C53: Meta description | D53: Passenger cabins built to order: durable construction with a choice of finishes, lighting, flooring and fixtures for residential and commercial elevators. | G53: Google result snippet, aim for 150-160 characters
A54: /products/elevator-control-panel | B54: SEO | C54: Browser / search title | D54: Elevator Control Panel · Philbrick | G54: Shown in the browser tab and Google results
A55: /products/elevator-control-panel | B55: SEO | C55: Meta description | D55: Control panels that manage motion, safety, signalling and door operation for a smooth, reliable elevator, engineered and built in-house. | G55: Google result snippet, aim for 150-160 characters
A56: /products/elevator-control-panel/automatic-door-controller | B56: SEO | C56: Browser / search title | D56: Automatic Door Controller · Philbrick | G56: Shown in the browser tab and Google results
A57: /products/elevator-control-panel/automatic-door-controller | B57: SEO | C57: Meta description | D57: Xpert Main Board based Auto Door V3F Type Control Panel available in 8, 12 and 16 landing floor configurations with Full Collective Logic. Options include customized MRL enclosure, ARD functionality and control panel for Synchronous Motor (Gearless Machine). | G57: Google result snippet, aim for 150-160 characters
A58: /products/elevator-control-panel/hydraulic-controller | B58: SEO | C58: Browser / search title | D58: Hydraulic Controller · Philbrick | G58: Shown in the browser tab and Google results
A59: /products/elevator-control-panel/hydraulic-controller | B59: SEO | C59: Meta description | D59: Xpert and Elevat+ Main Board based Hydraulic Lift Control Panels for up to 8 landing floors, available for Automatic and Manual Door configurations. Options include DOL/Star-Delta Main Pump Starter, MRL application, Phase Sequence Corrector and Front & Rear Door operation. | G59: Google result snippet, aim for 150-160 characters
... A125: /quality-policy | B125: SEO | C125: Meta description | D125: Philbrick Technologies products and services constantly meet or exceed customer expectation. Each part undergoes stage wise and final inspection as per the Q.A. plan and Indian standard specification. | G125: Google result snippet, aim for 150-160 characters
A126: /quality-policy | B126: SEO | C126: Social share description | D126: Philbrick Technologies is an Ahmedabad-based manufacturer, exporter and supplier of elevator control panels, integrated controllers, automatic rescue devices, door operators, cabins, displays and complete elevator components.
A127: /vision-mission | B127: SEO | C127: Browser / search title | D127: Vision & Mission · Philbrick | G127: Shown in the browser tab and Google results
A128: /vision-mission | B128: SEO | C128: Meta description | D128: The mission and vision behind Philbrick Technologies: dependable elevator control, safety and signalling systems, engineered in-house. | G128: Google result snippet, aim for 150-160 characters
A129: /vision-mission | B129: SEO | C129: Social share description | D129: Philbrick Technologies is an Ahmedabad-based manufacturer, exporter and supplier of elevator control panels, integrated controllers, automatic rescue devices, door operators, cabins, displays and complete elevator components.

Sheet WordPress source
A1: WordPress page | B1: Title | C1: What it contained | D1: WordPress text | E1: Where it lives now | F1: Migration note | G1: Client Final Text
A2: WordPress: /company/ | B2: Company | C2: Real client content | D2: About the Philbrick Technologies (India) Pvt. Ltd. Philbrick controls India was founded in 1992 in Ahmedabad, a city of Gujarat, India with a main focus on providing automation solution by research and development and production of Control Instruments &amp; Control Panels. A teamwork of young &amp; professional entrepreneurial and engineers with apex of providing technical solution with economy, the proficiency, in depth techno -commercial knowledge has brought the results in front of you. Activity Company provides automation solution to various industries by producing microcontroller based instruments and control panels. We are specialized in understanding the application to fulfil the industrial requirements by providing the best efficient economical solutions. We offer our best proficient automation solutions by advance development techniques, hi-tech manufacturing process, systematic testing methodology and strong quality assessment. We have been catering our services to various industrial segments like Construction, Textile, Steel, Plastic, Paper, Glass, Power, Chemical and Pollution Control Equipment manufacturers etc. We have dedicated team with a special focus on Elevator Industry for providing Smarter, Safer and Simpler Control Panels and various accessories for the passenger lift. History In 1992 Philbrick started with low cost high performing Digital Temperature Indicators, Temperature Controllers and scanners. In 1994 Introduction of Programmable Temperature Profile Controller PC -2000 for the Dyeing machine was accepted by most of the dyeing and printing process houses as a preferred option for the replacement of imported controller from outside India. With a remarkable success story OEM demanded the complete solution from the Philbrick which led the company to enter the market of Industrial control panels and Philbrick started manufacturing Automation Control Panels in 1997. Having the brand image as a quality manufacturer, Elevator Manufacturer approa… | E2: /about + /milestone | F2: Migrated in full: About, Activity, History
A3: WordPress: /front-page/ | B3: Philbrick India | C3: Real client content | D3: Elevator Control Panel Elevat Plus Manual Door Controller Salient Features: RISC microprocessor-based High Speed clocked design which enhances the processing speed for better elevator control. Multi Functional keypad with 2 digits LED segment display. Programmable configuration &amp; Functionality makes flexible controlling. Programmable, Floor Designation like B,P,C,L-1,-2, etc, Fireman floor etc. DIP switch settable number of floors. Non Stop Functionality. Auto FAN/LIGHT functionality to save energy. Intelligent electronics STOP function. Auto / Attendant Mode. Supports simple Gate Lock &amp; Pre Gate Lock (OTIS type lock) configuration. Audio Buzzer O/P for Open Door condition in Manual Door. Call Buzzer O/P for Landing Floor Call prompting. Opto Coupler based Galvanic Isolation for all Inputs &amp; Outputs. Separate LED Indication for all Inputs &amp; Outputs. Hardware &amp; Digital Filtering in all the input to suppress effects of Electrical Noise. PTC protected all the Digital I/O to avoid failure due to field faults. Solid State Display Driver with Resettable Fuse protection. Faster learning &amp; simple maintenance. (0 reviews) Read more Elevator Control Panel Automatic Door Controller Salient Features: 16 Bit/ 32 Bit RISC microprocessor-based High Speed clocked design which enhance the processing speed for better elevator control. Multi Functional keypad with LCD 20 * 4 line display. Programmable configuration &amp; Functionality makes flexible controlling. Programmable Number of Floors, Floor Designation like B, P, C, L-1, -2, etc, Fireman floor, Home Landing Floor, Door Timings, Front &amp; Rear Door Operation etc. Non Stop, VIP Mode &amp; HALT Functionality. Password protected trip setting. Self Diagnostic/ Debugging Mode for Onsite troubleshooting. Auto FAN/ LIGHT functionality to save energy. Intelligent electronics STOP function. Auto/ Attendant Mode. Audio Buzzer O/P for Open Door condition in Manual Door. Call Buzzer O/P for Landing Floor Call prom… | E3: / | F3: Product showcase migrated to the homepage range section
A4: WordPress: /vision-mission/ | B4: Vision & Mission | C4: Demo text (Lorem ipsum) | D4: Coming soon. | E4: /vision-mission | F4: WordPress held Lorem ipsum; new copy written
A5: WordPress: /milestone-awards/ | B5: Milestone (Awards) | C5: Demo text (Lorem ipsum) | D5: Coming soon. | E5: /milestone | F5: WordPress held Lorem ipsum; timeline built from the Company history
A6: WordPress: /news-events/ | B6: News & Events | C6: Demo text (Lorem ipsum) | D6: Coming soon. | E6: /news-events | F6: WordPress held Lorem ipsum; page exists with an empty state
A7: WordPress: /privacy-policy/ | B7: Privacy policy | C7: Real client content | D7: At Philbrick Technologies India Pvt Limited, we place paramount importance on safeguarding your personal data. This Privacy Policy ("Policy") is formulated by us, acting as the data controller, to provide you with insights into how we collect and process the personal data you submit or disclose. We also operate as a data controller when processing personal data obtained through third parties. The objective of this Policy is to ensure that you are well-informed about our data practices. We encourage you to read this Privacy Policy carefully. If you do not wish your personal data to be used by us as set out in this Privacy Policy, please do not provide us with your personal data. Please note that in such a case, we may not be able to provide you with our services, you may not have access to and/or be able to use some features of the Website, and your customer experience may be impacted. Information We Collect We may collect information that can identify you ("Personal Information"), such as your name, email address, and telephone number when you register for an account with us. We may also collect other information, such as your location, device information, and usage data, through cookies and other tracking technologies. We use the information we collect to provide and improve our services to you, to communicate with you, and to personalize your experience with the App. We may also use your information to comply with legal obligations or to protect our rights and interests. Data Retention and Security We will retain your Personal Information for as long as necessary to provide you with the services and to comply with our legal obligations. We take reasonable measures to protect your Personal Information from unauthorized access and use. Your Rights and Choices You have the right to access, correct, and delete your Personal Information. You may also choose to optout of receiving certain communications from us. If you have any questions or concerns about your privacy r… | E7: /privacy-policy | F7: Migrated in full, section for section
A8: WordPress: /quality-policy/ | B8: Quality Policy | C8: Real client content | D8: Philbrick Technologies (India) Pvt. Ltd. products and services, which constantly meet or exceed customer’s expectation and implied needs together with safety at customer’s premises. Each produced parts is undergone through strict quality inspection as per the quality plan as per Standards. Philbrick Technologies (India) Pvt. Ltd. prepare and submit the quality plan of their order execution and upkeep the quality record as per ISO certification. The procured material is 100% chemically and physically tested and undergone through the strict quality supervision by the company. Strict quality checks, records and test certificates edge the final finish product of high quality without any manufacturing defects. Thus Philbrick Technologies (India) Pvt. Ltd. always guarantee their products. The quality assurance plan approved by all leading engineering consultants and industrial giants are strictly being followed with upkeep of certifications till the dispatch of the parts. Each part is undergone through stage wise and final inspection as per Q.A. plan and tested as per Indian standard specification. | E8: /quality-policy | F8: Migrated in full (4 clauses)
A9: WordPress: /sample-page/ | B9: Sample Page | C9: Demo text (Lorem ipsum) | D9: This is an example page. It's different from a blog post because it will stay in one place and will show up in your site navigation (in most themes). Most people start with an About page that introduces them to potential site visitors. It might say something like this: Hi there! I'm a bike messenger by day, aspiring actor by night, and this is my website. I live in Los Angeles, have a great dog named Jack, and I like pi&#241;a coladas. (And gettin' caught in the rain.) ...or something like this: The XYZ Doohickey Company was founded in 1971, and has been providing quality doohickeys to the public ever since. Located in Gotham City, XYZ employs over 2,000 people and does all kinds of awesome things for the Gotham community. As a new WordPress user, you should go to your dashboard to delete this page and create new pages for your content. Have fun! | E9: (not migrated) | F9: WordPress default sample page, no client content
A10: WordPress: /career/ | B10: Career | C10: Real client content | D10: Working at Philbrick Technologies (India) Pvt. Ltd. might seem anarchic at times, but it’s never dreary. There is always something happening that keeps the passion flowing continually. The work is such, after all. It requires fervor that comes from inside and builds brands that endure. Philbrick Technologies (India) Pvt. Ltd. is not a single, person-centric company. It is a family where every person and his ideas are treated equally. We even undertake training programmers at various levels, so as to ensure that every employee works to the best of his or her capabilities. Mail your resume on hr.philbrickindia@gmail.com | E10: /career | F10: Migrated in full, including the HR inbox
A11: WordPress: /contact-us/ | B11: Contact Us | C11: Real client content | D11: Philbrick Technologies (India) Pvt. Ltd. Address: Plot No. 69, Road No. 6, G.I.D.C. Kathwada, Ahmedabad 382 430 India. Phone: +91 84012 19941 +91 93740 22660 +91 98250 09420 +91 99789 86631 OR Chat On Email: philbrick@philbrickindia.com philbrick_controls@yahoo.com sales@philbrickindia.com | E11: /contact | F11: Migrated in full: address, 4 phones, 3 emails, WhatsApp
A12: WordPress: /inquiry/ | B12: Inquiry | C12: Real client content | D12: Please fill in this and we will contact you soon. Click Here : philbrick@philbrickindia.com | E12: /contact | F12: Form migrated; every WordPress field is present
A13: WordPress: /download/ | B13: Download | C13: Real client content | D13: Sorry There Id Nothing To Download Right Now. Visit Again Later. | E13: /downloads | F13: Migrated, including the empty-state wording
A14: WordPress: /step-brochure/ | B14: Step Brochure | C14: Real client content | D14: Step Brochure Download Brochure | E14: /downloads | F14: Brochure link migrated (2023catalog.pdf)
A15: WordPress: /shop/ | B15: Shop | C15: Empty | E15: /products | F15: All 38 products migrated with features and spec tables
A16: WordPress: /infrastructure/ | B16: Infrastructure | C16: Empty | E16: /infrastructure | F16: WordPress page was empty; new page written
A17: WordPress: /network/ | B17: Network | C17: Empty | E17: /network | F17: WordPress page was empty; new page written

Sheet Product source
A1: Product page | B1: Product | C1: WordPress slug | D1: Salient features carried across | E1: Specification table | F1: Photos | G1: Client Final Text
A2: /products/elevator-control-panel | B2: Automatic Door Controller | C2: automatic-door-controller | D2: 18 | E2: Yes | F2: 3
A3: /products/elevator-control-panel | B3: Manual Door Controller | C3: manual-door-controller | D3: 18 | E3: Yes | F3: 3
A4: /products/elevator-control-panel | B4: Hydraulic Controller | C4: hydraulic-controller | D4: 9 | E4: Yes | F4: 2
A5: /products/integrated-control-panel | B5: Parallel Type Controller | C5: parallel-type-controller | D5: 15 | E5: Yes | F5: 2
A6: /products/integrated-control-panel | B6: Serial Can Bus Type Controller | C6: serial-can-bus-type-controller | D6: 19 | E6: Yes | F6: 1
A7: /products/integrated-control-panel | B7: MRL Control Panel | C7: mrl-control-panel | D7: 19 | E7: Yes | F7: 1
A8: /products/elevator-iot | B8: Elevator - IOT | C8: elevator-iot | D8: 0 | E8: No | F8: 1
A9: /products/ard | B9: ARD (Automatic Rescue Device) | C9: automatic-rescue-device | D9: 9 | E9: Yes | F9: 2
A10: /products/lift-master | B10: Lift Master - Door Operator Controller | C10: lift-master-door-operator-controller | D10: 6 | E10: Yes | F10: 1
A11: /products/synergy-auto-door | B11: 2-Panel Centre Opening | C11: 2-panel-centre-opening | D11: 15 | E11: Yes | F11: 5
A12: /products/synergy-auto-door | B12: 2-Panel Telescopic/Side Opening | C12: 2-panel-telescopic-side-opening | D12: 14 | E12: Yes | F12: 4
A13: /products/synergy-auto-door | B13: 4-Panel Centre Opening | C13: 4-panel-centre-opening | D13: 14 | E13: Yes | F13: 4
... A39: /products/step-products | B39: STEP Products | C39: step-products | D39: 8 | E39: No | F39: 5
